{"id": "tpKw1KGlI2k", "title": "LOS CADETES DE LINARES VIVO PRESO", "formats": [{"asr": 48000, "filesize": 1050634, "format_id": "249", "format_note": "tiny", "fps": null, "height": null, "quality": 0, "tbr": 53.83, "url": "https://rr5---sn-0opoxu-ihv6.googlevideo.com/videoplayback?expire=1670735246&ei=LhGVY8iyHdXtkga5rZ-YBQ&ip=189.173.225.87&id=o-ANCWZXPe6fx1uvP2-y0QTV1Vcx9xcqQL3X-1l66oSBiH&itag=249&source=youtube&requiressl=yes&mh=gE&mm=31%2C29&mn=sn-0opoxu-ihv6%2Csn-q4flrnld&ms=au%2Crdu&mv=m&mvi=5&pl=24&initcwndbps=753750&vprv=1&mime=audio%2Fwebm&ns=-jVprgcnRCCAg61i5LoBmx0J&gir=yes&clen=1050634&dur=156.141&lmt=1631902760752994&mt=1670713269&fvip=2&keepalive=yes&fexp=24001373%2C24007246&c=WEB&txp=5311222&n=gEuXsTTL55B_fuWBF&sparams=expire%2Cei%2Cip%2Cid%2Citag%2Csource%2Crequiressl%2Cvprv%2Cmime%2Cns%2Cgir%2Cclen%2Cdur%2Clmt&lsparams=mh%2Cmm%2Cmn%2Cms%2Cmv%2Cmvi%2Cpl%2Cinitcwndbps&lsig=AG3C_xAwRAIgEn23upFPivUK2GBLvcVINjxFWdbMWF2X8pwrDcqi9EsCIBDFJ6u7Sg8T2X2_WVDPsnZAZ_lMs3DBnl5UK3GF476S&sig=AOq0QJ8wRAIgLjyIChsKMkhSbp6Lg-UXAVMIVo78LzjqpWwTq-MQ42wCIEK4LxJ7e1U66jiM5mXjm89SGGIVoY6YmKJXUWvxhX49", "width": null, "ext": "webm", "vcodec": "none", "acodec": "opus", "abr": 53.83, "downloader_options": {"http_chunk_size": 10485760}, "container": "webm_dash", "format": "249 - audio only (tiny)", "protocol": "https", "http_headers": {"User-Agent": "Mozilla/5.0 (Windows NT 10.0; Win64; x64) AppleWebKit/537.36 (KHTML, like Gecko) Chrome/69.0.3497.76 Safari/537.36", "Accept-Charset": "ISO-8859-1,utf-8;q=0.7,*;q=0.7", "Accept": "text/html,application/xhtml+xml,application/xml;q=0.9,*/*;q=0.8", "Accept-Encoding": "gzip, deflate", "Accept-Language": "en-us,en;q=0.5"}}, {"asr": 48000, "filesize": 1384784, "format_id": "250", "format_note": "tiny", "fps": null, "height": null, "quality": 0, "tbr": 70.95, "url": "https://rr5---sn-0opoxu-ihv6.googlevideo.com/videoplayback?expire=1670735246&ei=LhGVY8iyHdXtkga5rZ-YBQ&ip=189.173.225.87&id=o-ANCWZXPe6fx1uvP2-y0QTV1Vcx9xcqQL3X-1l66oSBiH&itag=250&source=youtube&requiressl=yes&mh=gE&mm=31%2C29&mn=sn-0opoxu-ihv6%2Csn-q4flrnld&ms=au%2Crdu&mv=m&mvi=5&pl=24&initcwndbps=753750&vprv=1&mime=audio%2Fwebm&ns=-jVprgcnRCCAg61i5LoBmx0J&gir=yes&clen=1384784&dur=156.141&lmt=1631902761144856&mt=1670713269&fvip=2&keepalive=yes&fexp=24001373%2C24007246&c=WEB&txp=5311222&n=gEuXsTTL55B_fuWBF&sparams=expire%2Cei%2Cip%2Cid%2Citag%2Csource%2Crequiressl%2Cvprv%2Cmime%2Cns%2Cgir%2Cclen%2Cdur%2Clmt&lsparams=mh%2Cmm%2Cmn%2Cms%2Cmv%2Cmvi%2Cpl%2Cinitcwndbps&lsig=AG3C_xAwRQIhALqngUrToOqEBgQv4EjJzT3L46mCjpS07mP6Bmn2B_oTAiAyl32ruU0TGiMRD9ym3UjZ2sr_uNamEaT7-7tWJPtjAQ%3D%3D&sig=AOq0QJ8wRQIgFZvIgIf3HtZ6d-zkt2XEhoOEi_82pVo1Bh539VkMVr4CIQC4vu11TWu6dOjZ1tzBk-uCFpKQUbzk3I8rm0YodiQx8A==", "width": null, "ext": "webm", "vcodec": "none", "acodec": "opus", "abr": 70.95, "downloader_options": {"http_chunk_size": 10485760}, "container": "webm_dash", "format": "250 - audio only (tiny)", "protocol": "https", "http_headers": {"User-Agent": "Mozilla/5.0 (Windows NT 10.0; Win64; x64) AppleWebKit/537.36 (KHTML, like Gecko) Chrome/69.0.3497.76 Safari/537.36", "Accept-Charset": "ISO-8859-1,utf-8;q=0.7,*;q=0.7", "Accept": "text/html,application/xhtml+xml,application/xml;q=0.9,*/*;q=0.8", "Accept-Encoding": "gzip, deflate", "Accept-Language": "en-us,en;q=0.5"}}, {"asr": 44100, "filesize": 2528262, "format_id": "140", "format_note": "tiny", "fps": null, "height": null, "quality": 0, "tbr": 129.507, "url": "https://rr5---sn-0opoxu-ihv6.googlevideo.com/videoplayback?expire=1670735246&ei=LhGVY8iyHdXtkga5rZ-YBQ&ip=189.173.225.87&id=o-ANCWZXPe6fx1uvP2-y0QTV1Vcx9xcqQL3X-1l66oSBiH&itag=140&source=youtube&requiressl=yes&mh=gE&mm=31%2C29&mn=sn-0opoxu-ihv6%2Csn-q4flrnld&ms=au%2Crdu&mv=m&mvi=5&pl=24&initcwndbps=753750&vprv=1&mime=audio%2Fmp4&ns=-jVprgcnRCCAg61i5LoBmx0J&gir=yes&clen=2528262&dur=156.177&lmt=1631900340091048&mt=1670713269&fvip=2&keepalive=yes&fexp=24001373%2C24007246&c=WEB&txp=5311222&n=gEuXsTTL55B_fuWBF&sparams=expire%2Cei%2Cip%2Cid%2Citag%2Csource%2Crequiressl%2Cvprv%2Cmime%2Cns%2Cgir%2Cclen%2Cdur%2Clmt&lsparams=mh%2Cmm%2Cmn%2Cms%2Cmv%2Cmvi%2Cpl%2Cinitcwndbps&lsig=AG3C_xAwRAIgNFNaG1WBAB1hG0TXjuQTUtFEMtHbzZBBzZYY_Jfo0kgCIDCBN3W-e7KMy9lofnHK7UxRKu2sUe4Tn7Flodcp-6fL&sig=AOq0QJ8wRAIgI3dW9DP6avcjKFNfIKz4oJ2ktuqwP_wF22IlHnmxdmoCICjsiaVpENSMCV8eKVVpOcI2aq6rCbwas0BOLthkCGv0", "width": null, "ext": "m4a", "vcodec": "none", "acodec": "mp4a.40.2", "abr": 129.507, "downloader_options": {"http_chunk_size": 10485760}, "container": "m4a_dash", "format": "140 - audio only (tiny)", "protocol": "https", "http_headers": {"User-Agent": "Mozilla/5.0 (Windows NT 10.0; Win64; x64) AppleWebKit/537.36 (KHTML, like Gecko) Chrome/69.0.3497.76 Safari/537.36", "Accept-Charset": "ISO-8859-1,utf-8;q=0.7,*;q=0.7", "Accept": "text/html,application/xhtml+xml,application/xml;q=0.9,*/*;q=0.8", "Accept-Encoding": "gzip, deflate", "Accept-Language": "en-us,en;q=0.5"}}, {"asr": 48000, "filesize": 2694472, "format_id": "251", "format_note": "tiny", "fps": null, "height": null, "quality": 0, "tbr": 138.053, "url": "https://rr5---sn-0opoxu-ihv6.googlevideo.com/videoplayback?expire=1670735246&ei=LhGVY8iyHdXtkga5rZ-YBQ&ip=189.173.225.87&id=o-ANCWZXPe6fx1uvP2-y0QTV1Vcx9xcqQL3X-1l66oSBiH&itag=251&source=youtube&requiressl=yes&mh=gE&mm=31%2C29&mn=sn-0opoxu-ihv6%2Csn-q4flrnld&ms=au%2Crdu&mv=m&mvi=5&pl=24&initcwndbps=753750&vprv=1&mime=audio%2Fwebm&ns=-jVprgcnRCCAg61i5LoBmx0J&gir=yes&clen=2694472&dur=156.141&lmt=1631902766857779&mt=1670713269&fvip=2&keepalive=yes&fexp=24001373%2C24007246&c=WEB&txp=5311222&n=gEuXsTTL55B_fuWBF&sparams=expire%2Cei%2Cip%2Cid%2Citag%2Csource%2Crequiressl%2Cvprv%2Cmime%2Cns%2Cgir%2Cclen%2Cdur%2Clmt&lsparams=mh%2Cmm%2Cmn%2Cms%2Cmv%2Cmvi%2Cpl%2Cinitcwndbps&lsig=AG3C_xAwRQIgMwoHyEs_rQ4dvZQHCmVvJ6gL6s6hgZ51m9p5CSdLv4YCIQDdTD77-QfU0aQ3YBFaKYe8ywp4VXThRcp3eEjkgjQSug%3D%3D&sig=AOq0QJ8wRQIhANg5n4v73kjrpzTL9tDX4zmtylc3oIdoX45qLkuOi9tsAiA9uCd246fC3pHhhQ8cN_hUu7DEbvTf82pCI0L4xUutZQ==", "width": null, "ext": "webm", "vcodec": "none", "acodec": "opus", "abr": 138.053, "downloader_options": {"http_chunk_size": 10485760}, "container": "webm_dash", "format": "251 - audio only (tiny)", "protocol": "https", "http_headers": {"User-Agent": "Mozilla/5.0 (Windows NT 10.0; Win64; x64) AppleWebKit/537.36 (KHTML, like Gecko) Chrome/69.0.3497.76 Safari/537.36", "Accept-Charset": "ISO-8859-1,utf-8;q=0.7,*;q=0.7", "Accept": "text/html,application/xhtml+xml,application/xml;q=0.9,*/*;q=0.8", "Accept-Encoding": "gzip, deflate", "Accept-Language": "en-us,en;q=0.5"}}, {"asr": null, "filesize": 289735, "format_id": "160", "format_note": "144p", "fps": 30, "height": 144, "quality": 0, "tbr": 14.852, "url": "https://rr5---sn-0opoxu-ihv6.googlevideo.com/videoplayback?expire=1670735246&ei=LhGVY8iyHdXtkga5rZ-YBQ&ip=189.173.225.87&id=o-ANCWZXPe6fx1uvP2-y0QTV1Vcx9xcqQL3X-1l66oSBiH&itag=160&aitags=133%2C134%2C135%2C160%2C242%2C243%2C244%2C278&source=youtube&requiressl=yes&mh=gE&mm=31%2C29&mn=sn-0opoxu-ihv6%2Csn-q4flrnld&ms=au%2Crdu&mv=m&mvi=5&pl=24&initcwndbps=753750&vprv=1&mime=video%2Fmp4&ns=-jVprgcnRCCAg61i5LoBmx0J&gir=yes&clen=289735&dur=156.055&lmt=1631900349610193&mt=1670713269&fvip=2&keepalive=yes&fexp=24001373%2C24007246&c=WEB&txp=5311222&n=gEuXsTTL55B_fuWBF&sparams=expire%2Cei%2Cip%2Cid%2Caitags%2Csource%2Crequiressl%2Cvprv%2Cmime%2Cns%2Cgir%2Cclen%2Cdur%2Clmt&lsparams=mh%2Cmm%2Cmn%2Cms%2Cmv%2Cmvi%2Cpl%2Cinitcwndbps&lsig=AG3C_xAwRQIgF7vidR_9SXu3_aN7EFahTTrgW_M9sv3DPOb2bB8kQ4kCIQDVuQ6spxc_JZQU5FQRs2cSDF0YPoorzDh-w9esVJ2EAg%3D%3D&sig=AOq0QJ8wRQIgYjqInQUY-AakQw5ODixSDpx87TUJOoGYRRD2HVtYBq8CIQD-U44DNVTcYg6-3tPBzFqWYEefYYPbpzlXJJgBcbviig==", "width": 192, "ext": "mp4", "vcodec": "avc1.4d400c", "acodec": "none", "vbr": 14.852, "downloader_options": {"http_chunk_size": 10485760}, "container": "mp4_dash", "format": "160 - 192x144 (144p)", "protocol": "https", "http_headers": {"User-Agent": "Mozilla/5.0 (Windows NT 10.0; Win64; x64) AppleWebKit/537.36 (KHTML, like Gecko) Chrome/69.0.3497.76 Safari/537.36", "Accept-Charset": "ISO-8859-1,utf-8;q=0.7,*;q=0.7", "Accept": "text/html,application/xhtml+xml,application/xml;q=0.9,*/*;q=0.8", "Accept-Encoding": "gzip, deflate", "Accept-Language": "en-us,en;q=0.5"}}, {"asr": null, "filesize": 444443, "format_id": "278", "format_note": "144p", "fps": 30, "height": 144, "quality": 0, "tbr": 22.783, "url": "https://rr5---sn-0opoxu-ihv6.googlevideo.com/videoplayback?expire=1670735246&ei=LhGVY8iyHdXtkga5rZ-YBQ&ip=189.173.225.87&id=o-ANCWZXPe6fx1uvP2-y0QTV1Vcx9xcqQL3X-1l66oSBiH&itag=278&aitags=133%2C134%2C135%2C160%2C242%2C243%2C244%2C278&source=youtube&requiressl=yes&mh=gE&mm=31%2C29&mn=sn-0opoxu-ihv6%2Csn-q4flrnld&ms=au%2Crdu&mv=m&mvi=5&pl=24&initcwndbps=753750&vprv=1&mime=video%2Fwebm&ns=-jVprgcnRCCAg61i5LoBmx0J&gir=yes&clen=444443&dur=156.055&lmt=1631904183724368&mt=1670713269&fvip=2&keepalive=yes&fexp=24001373%2C24007246&c=WEB&txp=5311222&n=gEuXsTTL55B_fuWBF&sparams=expire%2Cei%2Cip%2Cid%2Caitags%2Csource%2Crequiressl%2Cvprv%2Cmime%2Cns%2Cgir%2Cclen%2Cdur%2Clmt&lsparams=mh%2Cmm%2Cmn%2Cms%2Cmv%2Cmvi%2Cpl%2Cinitcwndbps&lsig=AG3C_xAwRQIgfDge4i-PX1qmu7sFX_jBCIyBqOfhuIpgvQwlbhvd9AACIQCUXP3kpQOL8M-80F6k2dQfXGFeNsc50qawA3TIUUYDGQ%3D%3D&sig=AOq0QJ8wRQIgcYh-cf4w071RpGMDmWPT-USIONDLxflLBgUe1bo579UCIQDMR0rVEpF1nULI5x24Z4mikz3BzMpFkUNl3WI3CE_Dxw==", "width": 192, "ext": "webm", "vcodec": "vp9", "acodec": "none", "vbr": 22.783, "downloader_options": {"http_chunk_size": 10485760}, "container": "webm_dash", "format": "278 - 192x144 (144p)", "protocol": "https", "http_headers": {"User-Agent": "Mozilla/5.0 (Windows NT 10.0; Win64; x64) AppleWebKit/537.36 (KHTML, like Gecko) Chrome/69.0.3497.76 Safari/537.36", "Accept-Charset": "ISO-8859-1,utf-8;q=0.7,*;q=0.7", "Accept": "text/html,application/xhtml+xml,application/xml;q=0.9,*/*;q=0.8", "Accept-Encoding": "gzip, deflate", "Accept-Language": "en-us,en;q=0.5"}}, {"asr": null, "filesize": 523948, "format_id": "133", "format_note": "240p", "fps": 30, "height": 240, "quality": 1, "tbr": 26.859, "url": "https://rr5---sn-0opoxu-ihv6.googlevideo.com/videoplayback?expire=1670735246&ei=LhGVY8iyHdXtkga5rZ-YBQ&ip=189.173.225.87&id=o-ANCWZXPe6fx1uvP2-y0QTV1Vcx9xcqQL3X-1l66oSBiH&itag=133&aitags=133%2C134%2C135%2C160%2C242%2C243%2C244%2C278&source=youtube&requiressl=yes&mh=gE&mm=31%2C29&mn=sn-0opoxu-ihv6%2Csn-q4flrnld&ms=au%2Crdu&mv=m&mvi=5&pl=24&initcwndbps=753750&vprv=1&mime=video%2Fmp4&ns=-jVprgcnRCCAg61i5LoBmx0J&gir=yes&clen=523948&dur=156.055&lmt=1631900349607913&mt=1670713269&fvip=2&keepalive=yes&fexp=24001373%2C24007246&c=WEB&txp=5311222&n=gEuXsTTL55B_fuWBF&sparams=expire%2Cei%2Cip%2Cid%2Caitags%2Csource%2Crequiressl%2Cvprv%2Cmime%2Cns%2Cgir%2Cclen%2Cdur%2Clmt&lsparams=mh%2Cmm%2Cmn%2Cms%2Cmv%2Cmvi%2Cpl%2Cinitcwndbps&lsig=AG3C_xAwRQIhAMJUaAOt-OzBA0sohk6_V9tGT3sq9G2oYB7BAt5ENXKqAiAJPI6wAuDpC_wIQRwc9rLUBq4FRJZyBv4j27qYdKfVmg%3D%3D&sig=AOq0QJ8wRAIgDUij2F5ItxRJCLjA145rSbM3Y5NwvVjTM0lfo_FYOMECIDXGDgT8A55VaXLfHko3ROY1F98uXrvERMzcBxXs_SH6", "width": 320, "ext": "mp4", "vcodec": "avc1.4d400d", "acodec": "none", "vbr": 26.859, "downloader_options": {"http_chunk_size": 10485760}, "container": "mp4_dash", "format": "133 - 320x240 (240p)", "protocol": "https", "http_headers": {"User-Agent": "Mozilla/5.0 (Windows NT 10.0; Win64; x64) AppleWebKit/537.36 (KHTML, like Gecko) Chrome/69.0.3497.76 Safari/537.36", "Accept-Charset": "ISO-8859-1,utf-8;q=0.7,*;q=0.7", "Accept": "text/html,application/xhtml+xml,application/xml;q=0.9,*/*;q=0.8", "Accept-Encoding": "gzip, deflate", "Accept-Language": "en-us,en;q=0.5"}}, {"asr": null, "filesize": 1144533, "format_id": "242", "format_note": "240p", "fps": 30, "height": 240, "quality": 1, "tbr": 58.673, "url": "https://rr5---sn-0opoxu-ihv6.googlevideo.com/videoplayback?expire=1670735246&ei=LhGVY8iyHdXtkga5rZ-YBQ&ip=189.173.225.87&id=o-ANCWZXPe6fx1uvP2-y0QTV1Vcx9xcqQL3X-1l66oSBiH&itag=242&aitags=133%2C134%2C135%2C160%2C242%2C243%2C244%2C278&source=youtube&requiressl=yes&mh=gE&mm=31%2C29&mn=sn-0opoxu-ihv6%2Csn-q4flrnld&ms=au%2Crdu&mv=m&mvi=5&pl=24&initcwndbps=753750&vprv=1&mime=video%2Fwebm&ns=-jVprgcnRCCAg61i5LoBmx0J&gir=yes&clen=1144533&dur=156.055&lmt=1631904183450041&mt=1670713269&fvip=2&keepalive=yes&fexp=24001373%2C24007246&c=WEB&txp=5311222&n=gEuXsTTL55B_fuWBF&sparams=expire%2Cei%2Cip%2Cid%2Caitags%2Csource%2Crequiressl%2Cvprv%2Cmime%2Cns%2Cgir%2Cclen%2Cdur%2Clmt&lsparams=mh%2Cmm%2Cmn%2Cms%2Cmv%2Cmvi%2Cpl%2Cinitcwndbps&lsig=AG3C_xAwRQIgFEBExLq5_DROwF77GEEDvEd0E_NUh6KitTF5WDnFNJsCIQCywYgjBnfMZDdV2Vl2AnS1s4aU2-x9Uvvmr8HfAKXguQ%3D%3D&sig=AOq0QJ8wRQIgGHTZEY3KP6BRgiKvWgCx82FxQ4cnnE2R2h75vpom0YwCIQC2YdIgVPnmdc2enU-3_gDWJWxydrqfTGU8H11YvP057g==", "width": 320, "ext": "webm", "vcodec": "vp9", "acodec": "none", "vbr": 58.673, "downloader_options": {"http_chunk_size": 10485760}, "container": "webm_dash", "format": "242 - 320x240 (240p)", "protocol": "https", "http_headers": {"User-Agent": "Mozilla/5.0 (Windows NT 10.0; Win64; x64) AppleWebKit/537.36 (KHTML, like Gecko) Chrome/69.0.3497.76 Safari/537.36", "Accept-Charset": "ISO-8859-1,utf-8;q=0.7,*;q=0.7", "Accept": "text/html,application/xhtml+xml,application/xml;q=0.9,*/*;q=0.8", "Accept-Encoding": "gzip, deflate", "Accept-Language": "en-us,en;q=0.5"}}, {"asr": null, "filesize": 778727, "format_id": "134", "format_note": "360p", "fps": 30, "height": 360, "quality": 2, "tbr": 39.92, "url": "https://rr5---sn-0opoxu-ihv6.googlevideo.com/videoplayback?expire=1670735246&ei=LhGVY8iyHdXtkga5rZ-YBQ&ip=189.173.225.87&id=o-ANCWZXPe6fx1uvP2-y0QTV1Vcx9xcqQL3X-1l66oSBiH&itag=134&aitags=133%2C134%2C135%2C160%2C242%2C243%2C244%2C278&source=youtube&requiressl=yes&mh=gE&mm=31%2C29&mn=sn-0opoxu-ihv6%2Csn-q4flrnld&ms=au%2Crdu&mv=m&mvi=5&pl=24&initcwndbps=753750&vprv=1&mime=video%2Fmp4&ns=-jVprgcnRCCAg61i5LoBmx0J&gir=yes&clen=778727&dur=156.055&lmt=1631900349606845&mt=1670713269&fvip=2&keepalive=yes&fexp=24001373%2C24007246&c=WEB&txp=5311222&n=gEuXsTTL55B_fuWBF&sparams=expire%2Cei%2Cip%2Cid%2Caitags%2Csource%2Crequiressl%2Cvprv%2Cmime%2Cns%2Cgir%2Cclen%2Cdur%2Clmt&lsparams=mh%2Cmm%2Cmn%2Cms%2Cmv%2Cmvi%2Cpl%2Cinitcwndbps&lsig=AG3C_xAwRgIhAMxw2XYtq7XhznNjmhjGle98_E_L-2mjbo_AWc_nqsoBAiEAq9QqlhlSemeieuMPJUmvoDaPPYssSdkfkZWkM6y4Wrk%3D&sig=AOq0QJ8wRQIgUeJc_kzTMLkZ7omQptGnaYYZVvC_tgjejpAbMUNKZvICIQCEzFQ07I8c2NEeU1_5pj5SL_CNU2XGsHycHm4RQFl_9A==", "width": 480, "ext": "mp4", "vcodec": "avc1.4d401e", "acodec": "none", "vbr": 39.92, "downloader_options": {"http_chunk_size": 10485760}, "container": "mp4_dash", "format": "134 - 480x360 (360p)", "protocol": "https", "http_headers": {"User-Agent": "Mozilla/5.0 (Windows NT 10.0; Win64; x64) AppleWebKit/537.36 (KHTML, like Gecko) Chrome/69.0.3497.76 Safari/537.36", "Accept-Charset": "ISO-8859-1,utf-8;q=0.7,*;q=0.7", "Accept": "text/html,application/xhtml+xml,application/xml;q=0.9,*/*;q=0.8", "Accept-Encoding": "gzip, deflate", "Accept-Language": "en-us,en;q=0.5"}}, {"asr": null, "filesize": 1933967, "format_id": "243", "format_note": "360p", "fps": 30, "height": 360, "quality": 2, "tbr": 99.142, "url": "https://rr5---sn-0opoxu-ihv6.googlevideo.com/videoplayback?expire=1670735246&ei=LhGVY8iyHdXtkga5rZ-YBQ&ip=189.173.225.87&id=o-ANCWZXPe6fx1uvP2-y0QTV1Vcx9xcqQL3X-1l66oSBiH&itag=243&aitags=133%2C134%2C135%2C160%2C242%2C243%2C244%2C278&source=youtube&requiressl=yes&mh=gE&mm=31%2C29&mn=sn-0opoxu-ihv6%2Csn-q4flrnld&ms=au%2Crdu&mv=m&mvi=5&pl=24&initcwndbps=753750&vprv=1&mime=video%2Fwebm&ns=-jVprgcnRCCAg61i5LoBmx0J&gir=yes&clen=1933967&dur=156.055&lmt=1631904183434816&mt=1670713269&fvip=2&keepalive=yes&fexp=24001373%2C24007246&c=WEB&txp=5311222&n=gEuXsTTL55B_fuWBF&sparams=expire%2Cei%2Cip%2Cid%2Caitags%2Csource%2Crequiressl%2Cvprv%2Cmime%2Cns%2Cgir%2Cclen%2Cdur%2Clmt&lsparams=mh%2Cmm%2Cmn%2Cms%2Cmv%2Cmvi%2Cpl%2Cinitcwndbps&lsig=AG3C_xAwRgIhAN3e3PnUHztcBzgUSaKn065ULe4R5X76qsdA4ZpqACysAiEA1dcadX8-ILJ1twLQvbAL0bINLT4Wj3hJFJfr1Cwe1kY%3D&sig=AOq0QJ8wRQIgSAAtrbfRIX_j-WCMO6j7u64YH3Ko2PCHVe_lTEMbW00CIQCugpgL2CufP_6D_yJttXKS9pYOswdyugSfFgJ16XL1vw==", "width": 480, "ext": "webm", "vcodec": "vp9", "acodec": "none", "vbr": 99.142, "downloader_options": {"http_chunk_size": 10485760}, "container": "webm_dash", "format": "243 - 480x360 (360p)", "protocol": "https", "http_headers": {"User-Agent": "Mozilla/5.0 (Windows NT 10.0; Win64; x64) AppleWebKit/537.36 (KHTML, like Gecko) Chrome/69.0.3497.76 Safari/537.36", "Accept-Charset": "ISO-8859-1,utf-8;q=0.7,*;q=0.7", "Accept": "text/html,application/xhtml+xml,application/xml;q=0.9,*/*;q=0.8", "Accept-Encoding": "gzip, deflate", "Accept-Language": "en-us,en;q=0.5"}}, {"asr": null, "filesize": 1377996, "format_id": "135", "format_note": "480p", "fps": 30, "height": 480, "quality": 3, "tbr": 70.641, "url": "https://rr5---sn-0opoxu-ihv6.googlevideo.com/videoplayback?expire=1670735246&ei=LhGVY8iyHdXtkga5rZ-YBQ&ip=189.173.225.87&id=o-ANCWZXPe6fx1uvP2-y0QTV1Vcx9xcqQL3X-1l66oSBiH&itag=135&aitags=133%2C134%2C135%2C160%2C242%2C243%2C244%2C278&source=youtube&requiressl=yes&mh=gE&mm=31%2C29&mn=sn-0opoxu-ihv6%2Csn-q4flrnld&ms=au%2Crdu&mv=m&mvi=5&pl=24&initcwndbps=753750&vprv=1&mime=video%2Fmp4&ns=-jVprgcnRCCAg61i5LoBmx0J&gir=yes&clen=1377996&dur=156.055&lmt=1631900349616478&mt=1670713269&fvip=2&keepalive=yes&fexp=24001373%2C24007246&c=WEB&txp=5311222&n=gEuXsTTL55B_fuWBF&sparams=expire%2Cei%2Cip%2Cid%2Caitags%2Csource%2Crequiressl%2Cvprv%2Cmime%2Cns%2Cgir%2Cclen%2Cdur%2Clmt&lsparams=mh%2Cmm%2Cmn%2Cms%2Cmv%2Cmvi%2Cpl%2Cinitcwndbps&lsig=AG3C_xAwRQIhANoSXMx1AaGNKiPx20H-t8yMOt8uc_sXcnDKHSzy8RLYAiBtNwqSzCgsvT7FpYzJFcyNz38ZFAMdHJWi3_RXUA0U0g%3D%3D&sig=AOq0QJ8wRQIgd6znl1Ozv2IiFxlrmnKravQhIOOWxcVxpg__ROijlQsCIQCi1b05jGdTg8gw-TWDD3QnEgQafdXLmj44ckPQIwqS-Q==", "width": 640, "ext": "mp4", "vcodec": "avc1.4d401e", "acodec": "none", "vbr": 70.641, "downloader_options": {"http_chunk_size": 10485760}, "container": "mp4_dash", "format": "135 - 640x480 (480p)", "protocol": "https", "http_headers": {"User-Agent": "Mozilla/5.0 (Windows NT 10.0; Win64; x64) AppleWebKit/537.36 (KHTML, like Gecko) Chrome/69.0.3497.76 Safari/537.36", "Accept-Charset": "ISO-8859-1,utf-8;q=0.7,*;q=0.7", "Accept": "text/html,application/xhtml+xml,application/xml;q=0.9,*/*;q=0.8", "Accept-Encoding": "gzip, deflate", "Accept-Language": "en-us,en;q=0.5"}}, {"asr": null, "filesize": 3078601, "format_id": "244", "format_note": "480p", "fps": 30, "height": 480, "quality": 3, "tbr": 157.821, "url": "https://rr5---sn-0opoxu-ihv6.googlevideo.com/videoplayback?expire=1670735246&ei=LhGVY8iyHdXtkga5rZ-YBQ&ip=189.173.225.87&id=o-ANCWZXPe6fx1uvP2-y0QTV1Vcx9xcqQL3X-1l66oSBiH&itag=244&aitags=133%2C134%2C135%2C160%2C242%2C243%2C244%2C278&source=youtube&requiressl=yes&mh=gE&mm=31%2C29&mn=sn-0opoxu-ihv6%2Csn-q4flrnld&ms=au%2Crdu&mv=m&mvi=5&pl=24&initcwndbps=753750&vprv=1&mime=video%2Fwebm&ns=-jVprgcnRCCAg61i5LoBmx0J&gir=yes&clen=3078601&dur=156.055&lmt=1631904183429967&mt=1670713269&fvip=2&keepalive=yes&fexp=24001373%2C24007246&c=WEB&txp=5311222&n=gEuXsTTL55B_fuWBF&sparams=expire%2Cei%2Cip%2Cid%2Caitags%2Csource%2Crequiressl%2Cvprv%2Cmime%2Cns%2Cgir%2Cclen%2Cdur%2Clmt&lsparams=mh%2Cmm%2Cmn%2Cms%2Cmv%2Cmvi%2Cpl%2Cinitcwndbps&lsig=AG3C_xAwRAIgQB2g-bMkJqe8q-sb9g4A2iqs7AvCj1zffATCt91qZF4CIEjZlv-5MHthYMC1UZiWTvM78xuQHBl1SmxbL7MPO46W&sig=AOq0QJ8wRQIgS2xOwIsk5SuhlrZDSXkgg5y5wvxu2P34KaxwI8S-_7ECIQCEbQfHH371frlNtN6T4CnDMmwlZA8wXIuh8hXanZn5_w==", "width": 640, "ext": "webm", "vcodec": "vp9", "acodec": "none", "vbr": 157.821, "downloader_options": {"http_chunk_size": 10485760}, "container": "webm_dash", "format": "244 - 640x480 (480p)", "protocol": "https", "http_headers": {"User-Agent": "Mozilla/5.0 (Windows NT 10.0; Win64; x64) AppleWebKit/537.36 (KHTML, like Gecko) Chrome/69.0.3497.76 Safari/537.36", "Accept-Charset": "ISO-8859-1,utf-8;q=0.7,*;q=0.7", "Accept": "text/html,application/xhtml+xml,application/xml;q=0.9,*/*;q=0.8", "Accept-Encoding": "gzip, deflate", "Accept-Language": "en-us,en;q=0.5"}}, {"asr": 44100, "filesize": null, "format_id": "18", "format_note": "360p", "fps": 30, "height": 360, "quality": 2, "tbr": 168.774, "url": "https://rr5---sn-0opoxu-ihv6.googlevideo.com/videoplayback?expire=1670735246&ei=LhGVY8iyHdXtkga5rZ-YBQ&ip=189.173.225.87&id=o-ANCWZXPe6fx1uvP2-y0QTV1Vcx9xcqQL3X-1l66oSBiH&itag=18&source=youtube&requiressl=yes&mh=gE&mm=31%2C29&mn=sn-0opoxu-ihv6%2Csn-q4flrnld&ms=au%2Crdu&mv=m&mvi=5&pl=24&initcwndbps=753750&vprv=1&mime=video%2Fmp4&ns=NpI09CV7RWH-Nb6WlyLxpIEJ&cnr=14&ratebypass=yes&dur=156.177&lmt=1662971984811667&mt=1670713269&fvip=2&fexp=24001373%2C24007246&c=WEB&txp=5318224&n=oEYfhJ3Agala8OXEI&sparams=expire%2Cei%2Cip%2Cid%2Citag%2Csource%2Crequiressl%2Cvprv%2Cmime%2Cns%2Ccnr%2Cratebypass%2Cdur%2Clmt&lsparams=mh%2Cmm%2Cmn%2Cms%2Cmv%2Cmvi%2Cpl%2Cinitcwndbps&lsig=AG3C_xAwRQIhAMYVgbnTH_Nw9_nrhnTWFcwAo1EWkoSFEST1UYLtBXYKAiAxvZMNaxpdJn0dg2uodmyePfyNY-2aLd72bpW5eUkY6g%3D%3D&sig=AOq0QJ8wRQIhAOoyAby2M_bXBrSvXTz1BqsBDaGyfFExenTxy-j1IzbwAiA7i5cdEuT-fhS9L-OSTGvqCciMwu0_W2mmrmPnDIy_SQ==", "width": 480, "ext": "mp4", "vcodec": "avc1.42001E", "acodec": "mp4a.40.2", "format": "18 - 480x360 (360p)", "protocol": "https", "http_headers": {"User-Agent": "Mozilla/5.0 (Windows NT 10.0; Win64; x64) AppleWebKit/537.36 (KHTML, like Gecko) Chrome/69.0.3497.76 Safari/537.36", "Accept-Charset": "ISO-8859-1,utf-8;q=0.7,*;q=0.7", "Accept": "text/html,application/xhtml+xml,application/xml;q=0.9,*/*;q=0.8", "Accept-Encoding": "gzip, deflate", "Accept-Language": "en-us,en;q=0.5"}}], "thumbnails": [{"height": 94, "url": "https://i.ytimg.com/vi/tpKw1KGlI2k/hqdefault.jpg?sqp=-oaymwEbCKgBEF5IVfKriqkDDggBFQAAiEIYAXABwAEG&rs=AOn4CLB00bIpOUuUrwEO_2PoCIGvy3mLMw", "width": 168, "resolution": "168x94", "id": "0"}, {"height": 110, "url": "https://i.ytimg.com/vi/tpKw1KGlI2k/hqdefault.jpg?sqp=-oaymwEbCMQBEG5IVfKriqkDDggBFQAAiEIYAXABwAEG&rs=AOn4CLDFPij0_TYHHb97z-L8l-_Pg6vyCg", "width": 196, "resolution": "196x110", "id": "1"}, {"height": 138, "url": "https://i.ytimg.com/vi/tpKw1KGlI2k/hqdefault.jpg?sqp=-oaymwEcCPYBEIoBSFXyq4qpAw4IARUAAIhCGAFwAcABBg==&rs=AOn4CLBgPNn98lW1RUN_Mg3ozqzhQkqqJA", "width": 246, "resolution": "246x138", "id": "2"}, {"height": 188, "url": "https://i.ytimg.com/vi/tpKw1KGlI2k/hqdefault.jpg?sqp=-oaymwEcCNACELwBSFXyq4qpAw4IARUAAIhCGAFwAcABBg==&rs=AOn4CLDSr2joJr48RG4B4JlAxwM5pkpIHA", "width": 336, "resolution": "336x188", "id": "3"}], "description": "", "upload_date": "20180228", "uploader": "Sin Mex", "uploader_id": "UC5TkvNgiWZYoaGU0-XUpk3A", "uploader_url": "http://www.youtube.com/channel/UC5TkvNgiWZYoaGU0-XUpk3A", "channel_id": "UC5TkvNgiWZYoaGU0-XUpk3A", "channel_url": "https://www.youtube.com/channel/UC5TkvNgiWZYoaGU0-XUpk3A", "duration": 156, "view_count": 28728, "average_rating": null, "age_limit": 0, "webpage_url": "https://www.youtube.com/watch?v=tpKw1KGlI2k", "categories": ["People & Blogs"], "tags": [], "is_live": null, "channel": "Sin Mex", "extractor": "youtube", "webpage_url_basename": "watch", "extractor_key": "Youtube", "playlist": null, "playlist_index": null, "thumbnail": "https://i.ytimg.com/vi/tpKw1KGlI2k/hqdefault.jpg?sqp=-oaymwEcCNACELwBSFXyq4qpAw4IARUAAIhCGAFwAcABBg==&rs=AOn4CLDSr2joJr48RG4B4JlAxwM5pkpIHA", "display_id": "tpKw1KGlI2k", "asr": 44100, "filesize": null, "format_id": "18", "format_note": "360p", "fps": 30, "height": 360, "quality": 2, "tbr": 168.774, "url": "https://rr5---sn-0opoxu-ihv6.googlevideo.com/videoplayback?expire=1670735246&ei=LhGVY8iyHdXtkga5rZ-YBQ&ip=189.173.225.87&id=o-ANCWZXPe6fx1uvP2-y0QTV1Vcx9xcqQL3X-1l66oSBiH&itag=18&source=youtube&requiressl=yes&mh=gE&mm=31%2C29&mn=sn-0opoxu-ihv6%2Csn-q4flrnld&ms=au%2Crdu&mv=m&mvi=5&pl=24&initcwndbps=753750&vprv=1&mime=video%2Fmp4&ns=NpI09CV7RWH-Nb6WlyLxpIEJ&cnr=14&ratebypass=yes&dur=156.177&lmt=1662971984811667&mt=1670713269&fvip=2&fexp=24001373%2C24007246&c=WEB&txp=5318224&n=oEYfhJ3Agala8OXEI&sparams=expire%2Cei%2Cip%2Cid%2Citag%2Csource%2Crequiressl%2Cvprv%2Cmime%2Cns%2Ccnr%2Cratebypass%2Cdur%2Clmt&lsparams=mh%2Cmm%2Cmn%2Cms%2Cmv%2Cmvi%2Cpl%2Cinitcwndbps&lsig=AG3C_xAwRQIhAMYVgbnTH_Nw9_nrhnTWFcwAo1EWkoSFEST1UYLtBXYKAiAxvZMNaxpdJn0dg2uodmyePfyNY-2aLd72bpW5eUkY6g%3D%3D&sig=AOq0QJ8wRQIhAOoyAby2M_bXBrSvXTz1BqsBDaGyfFExenTxy-j1IzbwAiA7i5cdEuT-fhS9L-OSTGvqCciMwu0_W2mmrmPnDIy_SQ==", "width": 480, "ext": "mp4", "vcodec": "avc1.42001E", "acodec": "mp4a.40.2", "format": "18 - 480x360 (360p)", "protocol": "https", "http_headers": {"User-Agent": "Mozilla/5.0 (Windows NT 10.0; Win64; x64) AppleWebKit/537.36 (KHTML, like Gecko) Chrome/69.0.3497.76 Safari/537.36", "Accept-Charset": "ISO-8859-1,utf-8;q=0.7,*;q=0.7", "Accept": "text/html,application/xhtml+xml,application/xml;q=0.9,*/*;q=0.8", "Accept-Encoding": "gzip, deflate", "Accept-Language": "en-us,en;q=0.5"}, "fulltitle": "LOS CADETES DE LINARES VIVO PRESO", "_filename": "LOS CADETES DE LINARES VIVO PRESO-tpKw1KGlI2k.mp4"}